{
  "credit": "Made with Blockbench",
  "textures": {
    "particle": "motherlode-copper-dungeon:block/zapper_trap_bottom",
    "bottom": "motherlode-copper-dungeon:block/zapper_trap_bottom",
    "blade": "motherlode-copper-dungeon:block/cutter_trap_blades",
    "side": "motherlode-copper-dungeon:block/cutter_trap_side",
    "top": "motherlode-copper-dungeon:block/cutter_trap_top",
    "detail": "motherlode-copper-dungeon:block/cutter_trap_detail"
  },
  "elements": [
    {
      "from": [
        0,
        0,
        0
      ],
      "to": [
        16,
        16,
        16
      ],
      "faces": {
        "north": {
          "uv": [
            0,
            0,
            16,
            16
          ],
          "texture": "#side"
        },
        "east": {
          "uv": [
            0,
            0,
            16,
            16
          ],
          "texture": "#side"
        },
        "south": {
          "uv": [
            0,
            0,
            16,
            16
          ],
          "texture": "#side"
        },
        "west": {
          "uv": [
            0,
            0,
            16,
            16
          ],
          "texture": "#side"
        },
        "up": {
          "uv": [
            0,
            0,
            16,
            16
          ],
          "texture": "#top"
        },
        "down": {
          "uv": [
            0,
            0,
            16,
            16
          ],
          "texture": "#bottom"
        }
      }
    },
    {
      "from": [
        7.5,
        17,
        7.5
      ],
      "to": [
        8.5,
        26,
        8.5
      ],
      "rotation": {
        "angle": 0,
        "axis": "y",
        "origin": [
          15.5,
          25,
          15.5
        ]
      },
      "faces": {
        "north": {
          "uv": [
            0,
            3,
            1,
            12
          ],
          "texture": "#detail"
        },
        "east": {
          "uv": [
            0,
            3,
            1,
            12
          ],
          "texture": "#detail"
        },
        "south": {
          "uv": [
            0,
            3,
            1,
            12
          ],
          "texture": "#detail"
        },
        "west": {
          "uv": [
            0,
            3,
            1,
            12
          ],
          "texture": "#detail"
        }
      }
    },
    {
      "from": [
        7,
        26,
        7
      ],
      "to": [
        9,
        28,
        9
      ],
      "rotation": {
        "angle": 0,
        "axis": "y",
        "origin": [
          15,
          24,
          16
        ]
      },
      "faces": {
        "north": {
          "uv": [
            3,
            0,
            5,
            2
          ],
          "texture": "#detail"
        },
        "east": {
          "uv": [
            3,
            0,
            5,
            2
          ],
          "texture": "#detail"
        },
        "south": {
          "uv": [
            3,
            0,
            5,
            2
          ],
          "texture": "#detail"
        },
        "west": {
          "uv": [
            3,
            0,
            5,
            2
          ],
          "texture": "#detail"
        },
        "up": {
          "uv": [
            3,
            0,
            5,
            2
          ],
          "texture": "#detail"
        },
        "down": {
          "uv": [
            3,
            0,
            5,
            2
          ],
          "texture": "#detail"
        }
      }
    },
    {
      "from": [
        7,
        21,
        7
      ],
      "to": [
        9,
        23,
        9
      ],
      "rotation": {
        "angle": 0,
        "axis": "y",
        "origin": [
          15,
          19,
          16
        ]
      },
      "faces": {
        "north": {
          "uv": [
            3,
            0,
            5,
            2
          ],
          "texture": "#detail"
        },
        "east": {
          "uv": [
            3,
            0,
            5,
            2
          ],
          "texture": "#detail"
        },
        "south": {
          "uv": [
            3,
            0,
            5,
            2
          ],
          "texture": "#detail"
        },
        "west": {
          "uv": [
            3,
            0,
            5,
            2
          ],
          "texture": "#detail"
        },
        "up": {
          "uv": [
            3,
            0,
            5,
            2
          ],
          "texture": "#detail"
        },
        "down": {
          "uv": [
            3,
            0,
            5,
            2
          ],
          "texture": "#detail"
        }
      }
    },
    {
      "from": [
        0,
        27,
        0
      ],
      "to": [
        16,
        27,
        16
      ],
      "rotation": {
        "angle": 0,
        "axis": "y",
        "origin": [
          15,
          25,
          16
        ]
      },
      "faces": {
        "up": {
          "uv": [
            0,
            0,
            16,
            16
          ],
          "texture": "#blade"
        },
        "down": {
          "uv": [
            0,
            0,
            16,
            16
          ],
          "rotation": 90,
          "texture": "#blade"
        }
      }
    },
    {
      "from": [
        0,
        22,
        0
      ],
      "to": [
        16,
        22,
        16
      ],
      "rotation": {
        "angle": 0,
        "axis": "y",
        "origin": [
          15,
          20,
          16
        ]
      },
      "faces": {
        "up": {
          "uv": [
            0,
            0,
            16,
            16
          ],
          "rotation": 180,
          "texture": "#blade"
        },
        "down": {
          "uv": [
            0,
            0,
            16,
            16
          ],
          "rotation": 90,
          "texture": "#blade"
        }
      }
    },
    {
      "from": [
        6.5,
        16,
        6.5
      ],
      "to": [
        9.5,
        17,
        9.5
      ],
      "rotation": {
        "angle": 0,
        "axis": "y",
        "origin": [
          15.5,
          24,
          15.5
        ]
      },
      "faces": {
        "north": {
          "uv": [
            0,
            3,
            3,
            4
          ],
          "texture": "#detail"
        },
        "east": {
          "uv": [
            0,
            3,
            3,
            4
          ],
          "texture": "#detail"
        },
        "south": {
          "uv": [
            0,
            3,
            3,
            4
          ],
          "texture": "#detail"
        },
        "west": {
          "uv": [
            0,
            3,
            3,
            4
          ],
          "texture": "#detail"
        },
        "up": {
          "uv": [
            0,
            0,
            3,
            3
          ],
          "texture": "#detail"
        }
      }
    }
  ],
  "display": {
    "thirdperson_righthand": {
      "rotation": [
        75,
        45,
        0
      ],
      "translation": [
        0,
        2.5,
        0
      ],
      "scale": [
        0.375,
        0.375,
        0.375
      ]
    },
    "thirdperson_lefthand": {
      "rotation": [
        75,
        45,
        0
      ],
      "translation": [
        0,
        2.5,
        0
      ],
      "scale": [
        0.375,
        0.375,
        0.375
      ]
    },
    "firstperson_righthand": {
      "rotation": [
        0,
        45,
        0
      ],
      "scale": [
        0.4,
        0.4,
        0.4
      ]
    },
    "firstperson_lefthand": {
      "rotation": [
        0,
        225,
        0
      ],
      "scale": [
        0.4,
        0.4,
        0.4
      ]
    },
    "ground": {
      "translation": [
        0,
        3,
        0
      ],
      "scale": [
        0.25,
        0.25,
        0.25
      ]
    },
    "gui": {
      "rotation": [
        30,
        225,
        0
      ],
      "translation": [
        0,
        -2,
        0
      ],
      "scale": [
        0.475,
        0.475,
        0.475
      ]
    },
    "head": {
      "scale": [
        0.9,
        0.9,
        0.9
      ]
    },
    "fixed": {
      "scale": [
        0.5,
        0.5,
        0.5
      ]
    }
  }
}